README.md
license
setup.py
arcond/CCM21Device.py
arcond/CCM21DeviceState.py
arcond/CCM21SlaveDevice.py
arcond/__init__.py
gateway_midea.egg-info/PKG-INFO
gateway_midea.egg-info/SOURCES.txt
gateway_midea.egg-info/dependency_links.txt
gateway_midea.egg-info/requires.txt
gateway_midea.egg-info/top_level.txt