Metadata-Version: 2.1
Name: gateway_midea
Version: 0.0.2
Summary: A package to control Midea CCM21 data converter modules
Home-page: https://github.com/oosilveir4/ccm21.py
Author: Henrique Silveira
Author-email: henrique@minimundo.com.br
Classifier: Programming Language :: Python :: 3
Classifier: License :: OSI Approved :: MIT License
Classifier: Operating System :: OS Independent
License-File: license
Requires-Dist: httpx>=0.24.1
Requires-Dist: xmltodict>=0.13.0
Requires-Dist: aiohttp>=3.8.5
